{
  "Satellite": "SatelliteXYZ",
  "TemperatureReadings": [
    {
      "Date": "2024-06-11",
      "SolarPanels": {
        "Unit": "Celsius",
        "Value": 30
      },
      "ElectronicsBox": {
        "Unit": "Celsius",
        "Value": 40
      },
      "Antennas": {
        "Unit": "Celsius",
        "Value": 25
      },
      "ThermalBlanket": {
        "Unit": "Celsius",
        "Value": 20
      }
    },
    {
      "Date": "2024-06-11 00:00:10",
      "SolarPanels": {
        "Unit": "Celsius",
        "Value": 0
      },
      "ElectronicsBox": {
        "Unit": "Celsius",
        "Value": 1
      },
      "Antennas": {
        "Unit": "Celsius",
        "Value": 4
      },
      "ThermalBlanket": {
        "Unit": "Celsius",
        "Value": 1
      }
    },
    {
      "Date": "2024-06-11 00:00:20",
      "SolarPanels": {
        "Unit": "Celsius",
        "Value": 0
      },
      "ElectronicsBox": {
        "Unit": "Celsius",
        "Value": 2
      },
      "Antennas": {
        "Unit": "Celsius",
        "Value": 1
      },
      "ThermalBlanket": {
        "Unit": "Celsius",
        "Value": 4
      }
    },
    {
      "Date": "2024-06-11 00:00:30",
      "SolarPanels": {
        "Unit": "Celsius",
        "Value": 0
      },
      "ElectronicsBox": {
        "Unit": "Celsius",
        "Value": 3
      },
      "Antennas": {
        "Unit": "Celsius",
        "Value": 1
      },
      "ThermalBlanket": {
        "Unit": "Celsius",
        "Value": 1
      }
    }
  ]
}